LICENSE
MANIFEST.in
README
chiki_avatar.py
setup.py
chiki_avatar.egg-info/PKG-INFO
chiki_avatar.egg-info/SOURCES.txt
chiki_avatar.egg-info/dependency_links.txt
chiki_avatar.egg-info/not-zip-safe
chiki_avatar.egg-info/top_level.txt