Metadata-Version: 1.0
Name: chiki-avatar
Version: 0.0.1
Summary: chiki avatar libs.
Home-page: https://github.com/endsh/chiki-avatar
Author: Linshao
Author-email: 438985635@qq.com
License: UNKNOWN
Platform: any
